basecommand/api/__init__.py
basecommand/api/aces.py
basecommand/api/basecommand.py
basecommand/api/datamover.py
basecommand/api/dataset.py
basecommand/api/dockerwrappers.py
basecommand/api/jobs.py
basecommand/api/kubewrappers.py
basecommand/api/measurements.py
basecommand/api/quickstart.py
basecommand/api/quickstart_cluster.py
basecommand/api/quickstart_project.py
basecommand/api/resource.py
basecommand/api/resultset.py
basecommand/api/search.py
basecommand/api/utils.py
basecommand/api/workspace.py
basecommand/command/__init__.py
basecommand/command/aces.py
basecommand/command/all_commands.py
basecommand/command/args_validation.py
basecommand/command/base_command.py
basecommand/command/batch.py
basecommand/command/completers.py
basecommand/command/data.py
basecommand/command/datamover/__init__.py
basecommand/command/datamover/export_dataset.py
basecommand/command/datamover/export_workspace.py
basecommand/command/datamover/import_dataset.py
basecommand/command/datamover/import_workspace.py
basecommand/command/datamover/utils.py
basecommand/command/datamover_command.py
basecommand/command/quickstart.py
basecommand/command/quickstart_cluster.py
basecommand/command/quickstart_project.py
basecommand/command/resource.py
basecommand/command/result.py
basecommand/command/workspace.py
basecommand/constants.py
basecommand/data/api/Ace.py
basecommand/data/api/AceCreateRequest.py
basecommand/data/api/AceHealth.py
basecommand/data/api/AceInstance.py
basecommand/data/api/AceInstancePrices.py
basecommand/data/api/AceInstancePricesResponse.py
basecommand/data/api/AceInstanceTypeEnum.py
basecommand/data/api/AceListResponse.py
basecommand/data/api/AceNodeRemapRequest.py
basecommand/data/api/AceProvider.py
basecommand/data/api/AceResponse.py
basecommand/data/api/AceSimplified.py
basecommand/data/api/AceStorageInfo.py
basecommand/data/api/AceType.py
basecommand/data/api/AceUpdate.py
basecommand/data/api/AlertAggregationType.py
basecommand/data/api/AlertDeliveryMode.py
ngcsdk-4.9.10.dist-info/METADATA
ngcsdk-4.9.10.dist-info/WHEEL
ngcsdk-4.9.10.dist-info/entry_points.txt
ngcsdk-4.9.10.dist-info/RECORD
