Metadata-Version: 2.1
Name: ngcsdk
Version: 4.9.10
Summary: NVIDIA GPU Cloud SDK
License: Apache-2.0
Author: NVIDIA CORPORATION
Requires-Python: >=3.9.16,<4.0
Classifier: License :: OSI Approved :: Apache Software License
Classifier: Programming Language :: Python :: 3
Classifier: Programming Language :: Python :: 3.10
Classifier: Programming Language :: Python :: 3.11
Classifier: Programming Language :: Python :: 3.12
Classifier: Programming Language :: Python :: 3.13
Provides-Extra: datamover
Provides-Extra: telemetry
Requires-Dist: aiofiles (>=23.2.1)
Requires-Dist: aiohttp (>=3.10.11)
Requires-Dist: boto3 (>=1.20.5)
Requires-Dist: botocore (>=1.37)
Requires-Dist: certifi (>=2024.7.4)
Requires-Dist: cryptography (>=43.0.1)
Requires-Dist: docker (>=6,<8)
Requires-Dist: google-api-core (>=2.2.2) ; extra == "datamover"
Requires-Dist: grpcio (>=1.56.0,<=1.70.0) ; extra == "datamover"
Requires-Dist: isodate (>=0.6.0)
Requires-Dist: opentelemetry-exporter-otlp-proto-grpc (>=1.20.0,<2.0.0) ; extra == "telemetry"
Requires-Dist: opentelemetry-instrumentation (>=0.41b0,<1.0) ; extra == "telemetry"
Requires-Dist: opentelemetry-sdk (>=1.20.0) ; extra == "telemetry"
Requires-Dist: packaging (>=24.0)
Requires-Dist: polling2 (>=0.5.0)
Requires-Dist: prettytable (>=2.0.0)
Requires-Dist: protobuf (>=4.21.1) ; extra == "datamover"
Requires-Dist: psutil (>=5.8.0)
Requires-Dist: python-dateutil (>=2.8.2)
Requires-Dist: requests (>=2.31)
Requires-Dist: requests-toolbelt (>=1.0.0)
Requires-Dist: rich (>=12.6.0)
Requires-Dist: shortuuid (>=1.0.11)
Requires-Dist: urllib3 (>=1.26,<3)
Requires-Dist: validators (>=0.21.0)
Project-URL: Documentation, https://docs.ngc.nvidia.com/sdk/
Project-URL: Homepage, https://ngc.nvidia.com/
